<?xml version="1.0" encoding="utf-8" ?>
<Defs>

  <BiomeDef>
    <defName>ROMB_HauntedForest</defName>
    <label>haunted forest</label>
    <description>Dense forests of seemingly dead trees interspersed with fertile clearings. The ecosystem is flooded with smaller prey, but far more dangerous predators. Similar to other forests, because of snow, it is slow to travel in winter.</description>
    <workerClass>RoMBiomes.BiomeWorker_HauntedForest</workerClass>
    <animalDensity>2.8</animalDensity>
    <plantDensity>0.55</plantDensity>
    <factionBaseSelectionWeight>0.2</factionBaseSelectionWeight>
    <pathCost_spring>1650</pathCost_spring>
    <pathCost_summer>1650</pathCost_summer>
    <pathCost_fall>1650</pathCost_fall>
    <pathCost_winter>27500</pathCost_winter>
    <texture>World/Biomes/ROMB_HauntedForest</texture>
    <soundsAmbient>
      <li>AmbientNightInsects_Standard</li>
    </soundsAmbient>
    <diseaseMtbDays>45</diseaseMtbDays>
    <diseases>
      <li>
        <diseaseInc>Disease_Flu</diseaseInc>
        <commonality>100</commonality>
      </li>
      <li>
        <diseaseInc>Disease_Plague</diseaseInc>
        <commonality>100</commonality>
      </li>
      <li>
        <diseaseInc>Disease_Malaria</diseaseInc>
        <commonality>100</commonality>
      </li>
      <li>
        <diseaseInc>Disease_FibrousMechanites</diseaseInc>
        <commonality>30</commonality>
      </li>
      <li>
        <diseaseInc>Disease_SensoryMechanites</diseaseInc>
        <commonality>30</commonality>
      </li>
      <li>
        <diseaseInc>Disease_GutWorms</diseaseInc>
        <commonality>50</commonality>
      </li>
      <li>
        <diseaseInc>Disease_MuscleParasites</diseaseInc>
        <commonality>50</commonality>
      </li>
    </diseases>
    <terrainsByFertility>
      <li>
        <terrain>ROMB_PitchSoil</terrain>
        <min>-999</min>
        <max>0.87</max>
      </li>
      <li>
        <terrain>ROMB_PitchSoilRich</terrain>
        <min>0.87</min>
        <max>999</max>
      </li>
    </terrainsByFertility>
    <terrainPatchMakers>
      <li>
        <perlinFrequency>0.02</perlinFrequency>
        <thresholds>
          <li>
            <terrain>ROMB_PitchMarshyTerrain</terrain>
            <min>0.32</min>
            <max>999</max>
          </li>
        </thresholds>
      </li>	
      <li>
        <perlinFrequency>0.015</perlinFrequency>
        <thresholds>
          <li>
            <terrain>ROMB_PitchSoilRich</terrain>
            <min>0.73</min>
            <max>0.80</max>
          </li>
          <li>
            <terrain>ROMB_PitchMud</terrain>
            <min>0.80</min>
            <max>0.93</max>
          </li>
          <li>
            <terrain>ROMB_PitchWaterShallow</terrain>
            <min>0.93</min>
            <max>1.06</max>
          </li>
          <li>
            <terrain>ROMB_PitchWaterDeep</terrain>
            <min>1.06</min>
            <max>999</max>
          </li>
        </thresholds>
      </li>
    </terrainPatchMakers>
    <baseWeatherCommonalities>
      <Clear>4</Clear>
      <Fog>8</Fog>
      <Rain>4</Rain>
      <DryThunderstorm>1</DryThunderstorm>
      <RainyThunderstorm>8</RainyThunderstorm>
      <FoggyRain>2</FoggyRain>
      <SnowGentle>4</SnowGentle>
      <SnowHard>8</SnowHard>
    </baseWeatherCommonalities>
    <wildPlants>
			<ROMB_BlackGrass>5.0</ROMB_BlackGrass>
			<ROMB_ThornBushTall>0.6</ROMB_ThornBushTall>
			<ROMB_ThornBush>0.6</ROMB_ThornBush>
			<ROMB_FateTree>0.5</ROMB_FateTree>
			<ROMB_DrainedPine>0.5</ROMB_DrainedPine>
			<ROMB_DrainedOak>0.5</ROMB_DrainedOak>
			<PlantRaspberry>0.1</PlantRaspberry>
			<PlantWildHealroot>0.05</PlantWildHealroot>
		</wildPlants>
    <wildAnimals>
			<Hare>1.00</Hare>
			<Squirrel>1.00</Squirrel>
			<Rat>0.8</Rat>
			<Deer>0.5</Deer>
			<WildBoar>0.5</WildBoar>
			<Turkey>0.5</Turkey>
			<Raccoon>0.4</Raccoon>
			<Tortoise>0.4</Tortoise>
			<Ibex>0.3</Ibex>
			<Boomrat>0.25</Boomrat>
			<Muffalo>0.2</Muffalo>
			<Boomalope>0.2</Boomalope>
			<Alpaca>0.1</Alpaca>
			<Emu>0.1</Emu>
			<Ostrich>0.1</Ostrich>
			<Gazelle>0.05</Gazelle>
			<WolfTimber>0.04</WolfTimber>
			<FoxRed>0.04</FoxRed>
			<Megasloth>0.04</Megasloth>
			<GrizzlyBear>0.022</GrizzlyBear>
			<Warg>0.012</Warg>
			<Cougar>0.012</Cougar>
      <Lynx>0.008</Lynx>
    </wildAnimals>
    <allowedPackAnimals>
      <li>Muffalo</li>
      <li>Alpaca</li>
    </allowedPackAnimals>
  </BiomeDef>

</Defs>
